latex_generator/__init__.py
latex_generator/latex_generator.py
latex_generator-0.6.dist-info/METADATA
latex_generator-0.6.dist-info/WHEEL
latex_generator-0.6.dist-info/entry_points.txt
latex_generator-0.6.dist-info/top_level.txt
latex_generator-0.6.dist-info/RECORD
