Metadata-Version: 2.1
Name: latex-generator
Version: 0.6
Requires-Dist: Pillow
